MANIFEST.in
README.md
setup.py
django_story_builder.egg-info/PKG-INFO
django_story_builder.egg-info/SOURCES.txt
django_story_builder.egg-info/dependency_links.txt
django_story_builder.egg-info/not-zip-safe
django_story_builder.egg-info/pbr.json
django_story_builder.egg-info/requires.txt
django_story_builder.egg-info/top_level.txt
story/__init__.py
story/admin.py
story/apps.py
story/content_processors.py
story/models.py
story/urls.py
story/views.py
story/management/__init__.py
story/management/commands/__init__.py
story/management/commands/export_stories.py
story/migrations/0001_initial.py
story/migrations/0002_auto_20151226_0750.py
story/migrations/0003_auto_20151226_0805.py
story/migrations/0004_auto_20151226_0807.py
story/migrations/0005_auto_20151228_1934.py
story/migrations/0006_auto_20151230_1717.py
story/migrations/0007_story_starting_scene.py
story/migrations/0008_scene_image.py
story/migrations/0009_auto_20160227_2125.py
story/migrations/0010_image_story.py
story/migrations/0011_auto_20160509_0258.py
story/migrations/0012_auto_20160526_0244.py
story/migrations/0013_auto_20160528_0528.py
story/migrations/0014_auto_20160604_2311.py
story/migrations/0015_auto_20160628_0510.py
story/migrations/__init__.py
story/templates/story/admin_import.html
story/templates/story/admin_import_audio.html
story/templates/story/index.html