Metadata-Version: 1.0
Name: django-story-builder
Version: 0.2.10
Summary: Django project for creating CYOAs
Home-page: https://gitlab.com/leith-john/django-story-builder
Author: John Leith
Author-email: leith.john@gmail.com
License: UNKNOWN
Platform: UNKNOWN
